LICENSE
MANIFEST.in
README.md
requirements.txt
setup.py
test_image-encoded.png
test_image.png
src/pystego.py
src/pystego.egg-info/PKG-INFO
src/pystego.egg-info/SOURCES.txt
src/pystego.egg-info/dependency_links.txt
src/pystego.egg-info/requires.txt
src/pystego.egg-info/top_level.txt
src/tools/colors.py
src/tools/decoding.py
src/tools/encoding.py
src/tools/encryption_tools.py
src/tools/interface.py
src/tools/translation_tools.py