Metadata-Version: 1.1
Name: pystego
Version: 0.0.21
Summary: A Python program that allows you to save secret messages in images
Home-page: https://github.com/MiquelMuntaner/pystego
Author: Miquel Muntaner
Author-email: miquemuntanerweb@gmail.com
License: UNKNOWN
Platform: UNKNOWN
Classifier: Programming Language :: Python :: 3
Classifier: Intended Audience :: Developers
Classifier: Intended Audience :: Education
Classifier: Intended Audience :: End Users/Desktop
Classifier: License :: OSI Approved :: MIT License
